LICENSE.GPL3
LICENSE.LGPL
MANIFEST.in
README.txt
setup.cfg
setup.py
PyRomfsImage/PyRomfsImage.py
PyRomfsImage/__init__.py
PyRomfsImage.egg-info/PKG-INFO
PyRomfsImage.egg-info/SOURCES.txt
PyRomfsImage.egg-info/dependency_links.txt
PyRomfsImage.egg-info/top_level.txt
docs/Makefile
docs/conf.py
docs/getting_started.rst
docs/index.rst
docs/make.bat